PySDMs/__init__.py
PySDMs/_main.py
PySDMs/internal/__init__.py
PySDMs/internal/fit.py
PySDMs/internal/interpolate.py
PySDMs/internal/validation_visuals.py
PySDMs/internal/test/data/env_train/env_train_cr_192.csv
PySDMs/internal/test/data/env_train/env_train_cr_192_metadata.csv
PySDMs/internal/test/outputs/holdout_192.csv
PySDMs-1.1.dist-info/LICENSE
PySDMs-1.1.dist-info/METADATA
PySDMs-1.1.dist-info/WHEEL
PySDMs-1.1.dist-info/top_level.txt
PySDMs-1.1.dist-info/RECORD
