Metadata-Version: 2.1
Name: PySDMs
Version: 1.1
Summary: An object-oriented class for semi-Auto ML for geospatial classification tasks.
Home-page: https://github.com/daniel-furman/PySDMs
Author: Daniel Ryan Furman
Author-email: dryanfurman@gmail.com
License: MIT
Platform: UNKNOWN
Classifier: Development Status :: 3 - Alpha
Classifier: Topic :: Utilities
Classifier: License :: OSI Approved :: MIT License
Classifier: Intended Audience :: Science/Research
Classifier: Operating System :: OS Independent
Classifier: Programming Language :: Python :: 3
Classifier: Topic :: Scientific/Engineering
Requires-Dist: numpy
Requires-Dist: pandas
Requires-Dist: sklearn
Requires-Dist: matplotlib
Requires-Dist: pycaret
Requires-Dist: pyimpute
Requires-Dist: geopandas
Requires-Dist: rasterio
